{"cameraMode":{"drawMode":0,"name":"Shaded","section":"Shading Mode"},"sceneLighting":false,"audioPlay":false,"sceneViewState":{"m_AlwaysRefresh":false,"showFog":true,"showSkybox":false,"showFlares":true,"showImageEffects":true,"showParticleSystems":true,"showVisualEffectGraphs":true,"m_FxEnabled":true},"in2DMode":false,"pivot":{"x":-2.0376882553100588,"y":3.75,"z":-4.615200042724609},"rotation":{"x":-0.3765701353549957,"y":0.522162675857544,"z":0.2754613161087036,"w":0.7139443755149841},"size":3.644972085952759,"orthographic":false}